lifelib/__init__.py
lifelib/_dirs.py
lifelib/commands/__init__.py
lifelib/commands/create.py
lifelib/libraries/appliedlife/model_parameters.xlsx
lifelib/libraries/appliedlife/IntegratedLife/__init__.py
lifelib/libraries/appliedlife/IntegratedLife/_system.json
lifelib/libraries/appliedlife/IntegratedLife/Assumptions/__init__.py
lifelib/libraries/appliedlife/IntegratedLife/Assumptions/_data/_dynamic_inputs
lifelib/libraries/appliedlife/IntegratedLife/BaseData/__init__.py
lifelib/libraries/appliedlife/IntegratedLife/ModelPoints/__init__.py
lifelib/libraries/appliedlife/IntegratedLife/ModelPoints/_data/_dynamic_inputs
lifelib/libraries/appliedlife/IntegratedLife/Mortality/__init__.py
lifelib/libraries/appliedlife/IntegratedLife/ProductBase/__init__.py
lifelib/libraries/appliedlife/IntegratedLife/Run/__init__.py
lifelib/libraries/appliedlife/IntegratedLife/Run/GLWB/__init__.py
lifelib/libraries/appliedlife/IntegratedLife/Run/GMXB/__init__.py
lifelib/libraries/appliedlife/IntegratedLife/Run/_data/_dynamic_inputs
lifelib/libraries/appliedlife/IntegratedLife/Scenarios/__init__.py
lifelib/libraries/appliedlife/IntegratedLife/Scenarios/_data/_dynamic_inputs
lifelib/libraries/appliedlife/economic_data/index_parameters.xlsx
lifelib/libraries/appliedlife/economic_data/risk_free_202212.xlsx
lifelib/libraries/appliedlife/economic_data/risk_free_202312.xlsx
lifelib/libraries/appliedlife/input_tables/assumptions_202212.xlsx
lifelib/libraries/appliedlife/input_tables/assumptions_202312.xlsx
lifelib/libraries/appliedlife/input_tables/mortality_tables.xlsx
lifelib/libraries/appliedlife/input_tables/product_spec_tables.xlsx
lifelib/libraries/appliedlife/model_point_data/model_point_2022Q4IF_GMXB.csv
lifelib/libraries/appliedlife/model_point_data/model_point_2023Q4IF_GMXB.csv
lifelib/libraries/appliedlife/model_point_data/model_point_202401NB_GMXB.csv
lifelib/libraries/assets/generate_bond_data.ipynb
lifelib/libraries/assets/BasicBonds/__init__.py
lifelib-0.11.0.dist-info/LICENSE.txt
lifelib-0.11.0.dist-info/METADATA
lifelib-0.11.0.dist-info/WHEEL
lifelib-0.11.0.dist-info/entry_points.txt
lifelib-0.11.0.dist-info/top_level.txt
lifelib-0.11.0.dist-info/RECORD
